airtiler
