Metadata-Version: 1.0
Name: airtiler
Version: 1.0.0
Summary: The airtiler generates training / test data for neural networks by downloading buildings from vector data from OpenStreetMap and the corresponding satellite images from Microsoft Bing Maps.
Home-page: https://github.com/mnboos/airtiler
Author: Martin Boos
Author-email: UNKNOWN
License: MIT
Keywords: machinelearning
Platform: UNKNOWN
